braspag_sdk/__init__.py
braspag_sdk/apps/__init__.py
braspag_sdk/apps/emv3ds/__init__.py
braspag_sdk/apps/emv3ds/data/__init__.py
braspag_sdk/apps/emv3ds/data/credentials.py
braspag_sdk/apps/emv3ds/environment.py
braspag_sdk/apps/emv3ds/requests/__init__.py
braspag_sdk/apps/emv3ds/requests/get_access_token.py
braspag_sdk/apps/emv3ds/services.py
braspag_sdk/apps/payments/__init__.py
braspag_sdk/apps/payments/data/__init__.py
braspag_sdk/apps/payments/data/address.py
braspag_sdk/apps/payments/data/credentials.py
braspag_sdk/apps/payments/data/credit_card.py
braspag_sdk/apps/payments/data/customer.py
braspag_sdk/apps/payments/data/payment.py
braspag_sdk/apps/payments/data/sale.py
braspag_sdk/apps/payments/environment.py
braspag_sdk/apps/payments/requests/__init__.py
braspag_sdk/apps/payments/requests/create_sale.py
braspag_sdk/apps/payments/requests/query_sale.py
braspag_sdk/apps/payments/requests/update_sale.py
braspag_sdk/apps/payments/services.py
braspag_sdk/apps/sop/__init__.py
braspag_sdk/apps/sop/data/__init__.py
braspag_sdk/apps/sop/data/credentials.py
braspag_sdk/apps/sop/environment.py
braspag_sdk/apps/sop/requests/__init__.py
braspag_sdk/apps/sop/requests/get_access_token.py
braspag_sdk/apps/sop/requests/get_oauth2_token.py
braspag_sdk/apps/sop/services.py
braspag_sdk/apps/split/__init__.py
braspag_sdk/apps/split/data/__init__.py
braspag_sdk/apps/split/data/credentials.py
braspag_sdk/apps/split/data/split_merchant.py
braspag_sdk/apps/split/data/split_payment.py
braspag_sdk/apps/split/environment.py
braspag_sdk/apps/split/requests/__init__.py
braspag_sdk/apps/split/requests/create_split_merchant.py
braspag_sdk/apps/split/requests/get_oauth2_token.py
braspag_sdk/apps/split/services.py
braspag_sdk/braspag.py
braspag_sdk/utils/__init__.py
braspag_sdk/utils/base_request.py
braspag_sdk/utils/object_json.py
braspag_sdk-0.0.7.dist-info/LICENSE
braspag_sdk-0.0.7.dist-info/METADATA
braspag_sdk-0.0.7.dist-info/WHEEL
braspag_sdk-0.0.7.dist-info/RECORD
