Metadata-Version: 2.1
Name: braspag-sdk
Version: 0.0.7
Summary: An unofficial Python SDK for Braspag
Home-page: https://github.com/romatallinn/braspagSdk-python
Keywords: braspag,sdk,python,cielo,api,ecommerce,brazil,payments
Author: Roman Sirokov
Author-email: sirokov@dizconto.com
Requires-Python: >=3.7,<4.0
Classifier: Development Status :: 4 - Beta
Classifier: Intended Audience :: Developers
Classifier: License :: OSI Approved :: MIT License
Classifier: Natural Language :: English
Classifier: Programming Language :: Python
Classifier: Programming Language :: Python :: 3
Classifier: Programming Language :: Python :: 3.7
Classifier: Programming Language :: Python :: 3.8
Classifier: Programming Language :: Python :: 3.9
Classifier: Programming Language :: Python :: 3.10
Classifier: Programming Language :: Python :: 3.11
Classifier: Programming Language :: Python :: 3.12
Requires-Dist: future (>=1.0.0,<2.0.0)
Requires-Dist: requests (>=2.31.0,<3.0.0)
Project-URL: Repository, https://github.com/romatallinn/braspagSdk-python
